breadslicer/__init__.py
breadslicer/application/__init__.py
breadslicer/application/app.py
breadslicer/application/renderer.py
breadslicer/application/slice.py
breadslicer/components/__init__.py
breadslicer/components/base.py
breadslicer/components/choice.py
breadslicer/components/confirm.py
breadslicer/components/editor.py
breadslicer/components/multiple_choice.py
breadslicer/components/password.py
breadslicer/components/text.py
breadslicer/main.py
breadslicer/py.typed
breadslicer/utility/__init__.py
breadslicer/utility/abstractdataclass.py
breadslicer/utility/command.py
breadslicer/utility/fs.py
breadslicer/utility/git.py
breadslicer/utility/package_installers.py
breadslicer/utility/pyenv.py
breadslicer/utility/python_installers.py
opinionated/__init__.py
opinionated/bread.py
opinionated/cleanup.py
opinionated/dependencies.py
opinionated/includes/Dockerfile.alpine
opinionated/includes/Dockerfile.debian
opinionated/includes/Dockerfile.python
opinionated/includes/Dockerfile.slim
opinionated/includes/coverage.gitlab-ci.yml
opinionated/includes/lib.gitlab-ci.yml
opinionated/includes/release.gitlab-ci.yml
opinionated/includes/service.gitlab-ci.yml
opinionated/includes/utils.gitlab-ci.yml
opinionated/project_types.py
opinionated/py.typed
opinionated/questions.py
opinionated/templates/.devcontainer/devcontainer.json
opinionated/templates/.dockerignore
opinionated/templates/.envrc
opinionated/templates/.flake8
opinionated/templates/.github/workflows/.keep
opinionated/templates/.gitignore
opinionated/templates/.gitlab/.keep
opinionated/templates/.gitlab-ci.yml
opinionated/templates/.pre-commit-config.yaml
opinionated/templates/.print_help.py
opinionated/templates/.vscode/extensions.json
opinionated/templates/.vscode/launch.json
opinionated/templates/.vscode/settings.json
opinionated/templates/.vscode/tasks.json
opinionated/templates/Dockerfile
opinionated/templates/Makefile
opinionated/templates/README.md
opinionated/templates/django/project_template/manage.py-tpl
breadslicer-0.0.6.post7.dist-info/METADATA
breadslicer-0.0.6.post7.dist-info/WHEEL
breadslicer-0.0.6.post7.dist-info/entry_points.txt
breadslicer-0.0.6.post7.dist-info/RECORD
