Metadata-Version: 2.1
Name: breadslicer
Version: 0.0.6.post7
Summary: Commandline utililty to create python projects from templates
Home-page: https://gitlab.com/mindsweeper/open-source/breadslicer
Author: Morten Rasmussen
Author-email: netrom1337@gmail.com
Requires-Python: >=3.10.7,<4.0.0
Classifier: Programming Language :: Python :: 3
Classifier: Programming Language :: Python :: 3.11
Classifier: Programming Language :: Python :: 3.12
Requires-Dist: inquirer (>=3.2.4,<4.0.0)
Requires-Dist: jinja2 (>=3.1.4,<4.0.0)
Project-URL: Documentation, https://mindsweeper.gitlab.io/open-source/breadslicer/
Project-URL: Repository, https://gitlab.com/mindsweeper/open-source/breadslicer
